AUTHORS
ChangeLog
LICENSE.txt
README.rst
requirements.txt
setup.cfg
setup.py
bypass/__init__.py
bypass/app.py
bypass.egg-info/PKG-INFO
bypass.egg-info/SOURCES.txt
bypass.egg-info/dependency_links.txt
bypass.egg-info/entry_points.txt
bypass.egg-info/not-zip-safe
bypass.egg-info/pbr.json
bypass.egg-info/requires.txt
bypass.egg-info/top_level.txt
tests/test_app.py