Metadata-Version: 1.1
Name: bypass
Version: 0.1.2
Summary: CLI password manager using GPG2.
Home-page: https://github.com/rjsberry/bypass
Author: Richard Berry
Author-email: rjsberry@protonmail.com
License: UNKNOWN
Platform: UNKNOWN
Classifier: Development Status :: 1 - Planning
Classifier: Environment :: Console
Classifier: Intended Audience :: End Users/Desktop
Classifier: License :: OSI Approved :: BSD License
Classifier: Natural Language :: English
Classifier: Operating System :: Unix
Classifier: Programming Language :: Python :: 3.6
